pynajax/__init__.py
pynajax/jax_core_bin_average.py
pynajax/jax_core_convolve.py
pynajax/jax_core_threshold.py
pynajax/jax_process_filtering.py
pynajax/jax_process_perievent.py
pynajax/utils.py
pynajax-0.2.1.dist-info/licenses/LICENSE
pynajax-0.2.1.dist-info/METADATA
pynajax-0.2.1.dist-info/WHEEL
pynajax-0.2.1.dist-info/top_level.txt
pynajax-0.2.1.dist-info/RECORD
