Metadata-Version: 2.4
Name: pynajax
Version: 0.2.1
Summary: A JAX backend for pynapple.
Author: pynajax authors
License: MIT License
Keywords: neuroscience,jax-backend,pynapple
Classifier: Intended Audience :: Science/Research
Classifier: Natural Language :: English
Classifier: Programming Language :: Python :: 3
Classifier: Programming Language :: Python :: 3.10
Requires-Python: >=3.8
License-File: LICENSE
Requires-Dist: jax>=0.4
Requires-Dist: typing_extensions>=4.6
Requires-Dist: numpy
Requires-Dist: jaxlib
Requires-Dist: pynapple
Requires-Dist: numba
Provides-Extra: dev
Requires-Dist: pip-tools; extra == "dev"
Requires-Dist: pytest; extra == "dev"
Requires-Dist: coverage; extra == "dev"
Requires-Dist: pytest-cov; extra == "dev"
Requires-Dist: matplotlib>=3.7; extra == "dev"
Requires-Dist: nox; extra == "dev"
Requires-Dist: ruff; extra == "dev"
Requires-Dist: flake8; extra == "dev"
Requires-Dist: Flake8-pyproject; extra == "dev"
Provides-Extra: docs
Requires-Dist: mkdocs; extra == "docs"
Requires-Dist: mkdocstrings[python]; extra == "docs"
Requires-Dist: mkdocs-section-index; extra == "docs"
Requires-Dist: mkdocs-gen-files; extra == "docs"
Requires-Dist: mkdocs-literate-nav>=0.6.1; extra == "docs"
Requires-Dist: mkdocs-gallery; extra == "docs"
Requires-Dist: mkdocs-material; extra == "docs"
Requires-Dist: mkdocs-autorefs>=0.5; extra == "docs"
Dynamic: license-file
